{"type":"FeatureCollection", "features": [
{"type":"Feature","geometry":{"type":"MultiPolygon","coordinates":[[[[-2.6462,49.4257],[-2.6229,49.4201],[-2.6478,49.4346],[-2.6529,49.4294],[-2.6462,49.4257]]],[[[-2.6623,49.4349],[-2.6718,49.4376],[-2.6751,49.4293],[-2.6565,49.4229],[-2.6623,49.4349]]]]},"properties":{"GID_1":"GGY.14_1","GID_0":"GGY","COUNTRY":"Guernsey","NAME_1":"Torteval","VARNAME_1":"NA","NL_NAME_1":"NA","TYPE_1":"Parish","ENGTYPE_1":"Parish","CC_1":"NA","HASC_1":"GG.TV","ISO_1":"NA"}}
]}