{"type": "Feature", "properties": {"GID_1": "SOM.9_1", "GID_0": "SOM", "COUNTRY": "Somalia", "NAME_1": "JubbadaDhexe", "VARNAME_1": "J.Dhexe|CentralJuba|MiddleJ", "NL_NAME_1": "NA", "TYPE_1": "Gobolka", "ENGTYPE_1": "Region", "CC_1": "NA", "HASC_1": "SO.JD", "ISO_1": "NA"}, "geometry": {"type": "MultiPolygon", "coordinates": [[[[43.35, 0.92], [43.5185, 0.6757], [43.4699, 0.6285], [43.3812, 0.5379], [43.2143, 0.3549], [43.2113, 0.3499], [43.1976, 0.3368], [43.1854, 0.3215], [43.1796, 0.3163], [42.73, 0.31], [42.63, 0.72], [42.43, 1.32], [42.2, 1.31], [41.4201, 1.26], [41.64, 1.94], [42.4, 1.95], [42.52, 1.88], [42.9, 1.52], [42.98, 1.46], [43.27, 1.03], [43.35, 0.92]]]]}}